tpu_inl/__init__.py
tpu_inl/autodetect.py
tpu_inl/backends/__init__.py
tpu_inl/backends/amd.py
tpu_inl/backends/cpu.py
tpu_inl/backends/cuda.py
tpu_inl/backends/directml.py
tpu_inl/backends/intel.py
tpu_inl/backends/tpu.py
tpu_inl/inference/__init__.py
tpu_inl/inference/batching.py
tpu_inl/inference/engine.py
tpu_inl/inference/kv_cache.py
tpu_inl/inference/speculative.py
tpu_inl/inference/streaming.py
tpu_inl/models/__init__.py
tpu_inl/models/complexity.py
tpu_inl/ops/__init__.py
tpu_inl/ops/fused_ops.py
tpu_inl/ops/inl_dynamics.py
tpu_inl/ops/moe_routing.py
tpu_inl/optimizers/__init__.py
tpu_inl/optimizers/autotuning.py
tpu_inl/optimizers/kernel_fusion.py
tpu_inl/optimizers/memory_layout.py
tpu_inl/optimizers/quantization.py
tpu_inl/optimizers/scheduling.py
tpu_inl-0.2.2.dist-info/METADATA
tpu_inl-0.2.2.dist-info/WHEEL
tpu_inl-0.2.2.dist-info/top_level.txt
tpu_inl-0.2.2.dist-info/RECORD
