Metadata-Version: 2.4
Name: tpu-inl
Version: 0.2.2
Summary: Cross-platform Integrator Neuron Layer acceleration for TPU, CUDA, AMD, Intel, DirectML
Home-page: https://github.com/Web3-League/tpu-inl
Author: Pacific Prime
Author-email: Pacific Prime <contact@pacific-prime.ai>
License: Apache-2.0
Project-URL: Homepage, https://github.com/Web3-League/tpu-inl
Project-URL: Repository, https://github.com/Web3-League/tpu-inl
Project-URL: Issues, https://github.com/Web3-League/tpu-inl/issues
Keywords: deep-learning,pytorch,tpu,cuda,amd,inference,acceleration
Classifier: Development Status :: 3 - Alpha
Classifier: Intended Audience :: Developers
Classifier: Intended Audience :: Science/Research
Classifier: License :: OSI Approved :: Apache Software License
Classifier: Operating System :: OS Independent
Classifier: Programming Language :: Python :: 3
Classifier: Programming Language :: Python :: 3.8
Classifier: Programming Language :: Python :: 3.9
Classifier: Programming Language :: Python :: 3.10
Classifier: Programming Language :: Python :: 3.11
Classifier: Programming Language :: Python :: 3.12
Classifier: Topic :: Scientific/Engineering :: Artificial Intelligence
Requires-Python: >=3.8
Requires-Dist: torch>=2.0.0
Requires-Dist: numpy>=1.21.0
Provides-Extra: cuda
Requires-Dist: triton>=2.0.0; extra == "cuda"
Provides-Extra: tpu
Requires-Dist: jax[tpu]>=0.4.0; extra == "tpu"
Provides-Extra: amd
Requires-Dist: triton>=2.0.0; extra == "amd"
Provides-Extra: intel
Requires-Dist: intel-extension-for-pytorch>=2.0.0; extra == "intel"
Provides-Extra: directml
Requires-Dist: torch-directml>=0.2.0; extra == "directml"
Provides-Extra: all
Requires-Dist: triton>=2.0.0; extra == "all"
Requires-Dist: jax>=0.4.0; extra == "all"
Provides-Extra: dev
Requires-Dist: pytest>=7.0.0; extra == "dev"
Requires-Dist: black>=23.0.0; extra == "dev"
Requires-Dist: isort>=5.12.0; extra == "dev"
Dynamic: author
Dynamic: home-page
Dynamic: requires-python
